aliyunsdkoutboundbot/__init__.py
aliyunsdkoutboundbot/endpoint.py
aliyunsdkoutboundbot/request/__init__.py
aliyunsdkoutboundbot/request/v20191226/ApplyNumberDistrictInfoParsingResultRequest.py
aliyunsdkoutboundbot/request/v20191226/AssignJobsRequest.py
aliyunsdkoutboundbot/request/v20191226/CancelJobsRequest.py
aliyunsdkoutboundbot/request/v20191226/ChangeResourceGroupRequest.py
aliyunsdkoutboundbot/request/v20191226/CreateBatchJobsRequest.py
aliyunsdkoutboundbot/request/v20191226/CreateBatchRepeatJobRequest.py
aliyunsdkoutboundbot/request/v20191226/CreateDialogueFlowRequest.py
aliyunsdkoutboundbot/request/v20191226/CreateDownloadUrlRequest.py
aliyunsdkoutboundbot/request/v20191226/CreateGlobalQuestionRequest.py
aliyunsdkoutboundbot/request/v20191226/CreateInstanceBindNumberRequest.py
aliyunsdkoutboundbot/request/v20191226/CreateInstanceRequest.py
aliyunsdkoutboundbot/request/v20191226/CreateIntentRequest.py
aliyunsdkoutboundbot/request/v20191226/CreateJobDataParsingTaskRequest.py
aliyunsdkoutboundbot/request/v20191226/CreateJobGroupExportTaskRequest.py
aliyunsdkoutboundbot/request/v20191226/CreateJobGroupRequest.py
aliyunsdkoutboundbot/request/v20191226/CreateNumberDistrictInfoDownloadUrlRequest.py
aliyunsdkoutboundbot/request/v20191226/CreateNumberDistrictInfoParsingTaskRequest.py
aliyunsdkoutboundbot/request/v20191226/CreateOutboundCallNumberRequest.py
aliyunsdkoutboundbot/request/v20191226/CreateScriptRequest.py
aliyunsdkoutboundbot/request/v20191226/CreateScriptWaveformRequest.py
aliyunsdkoutboundbot/request/v20191226/CreateTagRequest.py
aliyunsdkoutboundbot/request/v20191226/CreateTaskExportTaskRequest.py
aliyunsdkoutboundbot/request/v20191226/DeleteAllNumberDistrictInfoRequest.py
aliyunsdkoutboundbot/request/v20191226/DeleteContactBlockListRequest.py
aliyunsdkoutboundbot/request/v20191226/DeleteContactWhiteListRequest.py
aliyunsdkoutboundbot/request/v20191226/DeleteDialogueFlowRequest.py
aliyunsdkoutboundbot/request/v20191226/DeleteGlobalQuestionRequest.py
aliyun_python_sdk_outboundbot-1.6.2.dist-info/LICENSE
aliyun_python_sdk_outboundbot-1.6.2.dist-info/METADATA
aliyun_python_sdk_outboundbot-1.6.2.dist-info/WHEEL
aliyun_python_sdk_outboundbot-1.6.2.dist-info/top_level.txt
aliyun_python_sdk_outboundbot-1.6.2.dist-info/RECORD
